CJH/CJH.py
CJH/__init__.py
DV/DV.py
DV/__init__.py
LOEB/LOEB.py
LOEB/__init__.py
Text/Text.py
Text/__init__.py
UpdatedPixPlot/UpdatedPixPlot.py
UpdatedPixPlot/__init__.py
JATA_Tools-0.1.9.dist-info/LICENSE
JATA_Tools-0.1.9.dist-info/METADATA
JATA_Tools-0.1.9.dist-info/WHEEL
JATA_Tools-0.1.9.dist-info/top_level.txt
JATA_Tools-0.1.9.dist-info/RECORD
